text_translate/Translate_API.py
text_translate/__init__.py
text_translate-1.0.1.dist-info/LICENSE.txt
text_translate-1.0.1.dist-info/METADATA
text_translate-1.0.1.dist-info/WHEEL
text_translate-1.0.1.dist-info/top_level.txt
text_translate-1.0.1.dist-info/RECORD
