Metadata-Version: 2.1
Name: text-translate
Version: 1.0.1
Summary: Text translation API
Home-page: https://github.com/spicetech/translate
Author: SpiceTech
Author-email: contact@spicetech.in
License: UNKNOWN
Platform: UNKNOWN
Classifier: Programming Language :: Python :: 3
Classifier: License :: OSI Approved :: MIT License
Classifier: Operating System :: OS Independent
Requires-Python: >=3.6
